trulens/semconv/__init__.py
trulens/semconv/trace.py
trulens_semconv-1.2.9.dist-info/METADATA
trulens_semconv-1.2.9.dist-info/WHEEL
trulens_semconv-1.2.9.dist-info/RECORD
