Metadata-Version: 2.1
Name: trulens-semconv
Version: 1.2.9
Summary: Semantic conventions for spans produced by TruLens.
Home-page: https://trulens.org/
License: MIT
Author: Snowflake Inc.
Author-email: ml-observability-wg-dl@snowflake.com
Requires-Python: >=3.8, !=2.7.*, !=3.0.*, !=3.1.*, !=3.2.*, !=3.3.*, !=3.4.*, !=3.5.*, !=3.6.*, !=3.7.*
Classifier: Development Status :: 3 - Alpha
Classifier: License :: OSI Approved :: MIT License
Classifier: Operating System :: OS Independent
Classifier: Programming Language :: Python :: 3
Classifier: Programming Language :: Python :: 3.9
Classifier: Programming Language :: Python :: 3.10
Classifier: Programming Language :: Python :: 3.11
Classifier: Programming Language :: Python :: 3.12
Classifier: Programming Language :: Python :: 3.13
Requires-Dist: opentelemetry-semantic-conventions (>=0.48b0)
Project-URL: Documentation, https://trulens.org/getting_started/
Project-URL: Repository, https://github.com/truera/trulens
